pyxid2/__init__.py
pyxid2/constants.py
pyxid2/internal.py
pyxid2/keymaps.py
pyxid2/pyxid_impl.py
pyxid2-1.0.9.dist-info/COPYING
pyxid2-1.0.9.dist-info/METADATA
pyxid2-1.0.9.dist-info/WHEEL
pyxid2-1.0.9.dist-info/top_level.txt
pyxid2-1.0.9.dist-info/RECORD
