Metadata-Version: 2.2
Name: pyxid2
Version: 1.0.9
Summary: Python library for interfacing with Cedrus XID devices, e.g. StimTracker, Riponda, RB-x40, c-pod, and Lumina.
Home-page: http://www.github.com/cedrus-opensource/pyxid/
Author: Eugene Matsak
Author-email: developers@cedrus.com
Maintainer: Cedrus Corporation
Maintainer-email: developers@cedrus.com
License: BSD
Keywords: cedrus xid XID stimulus response data collection
Classifier: Intended Audience :: Developers
Classifier: License :: OSI Approved :: BSD License
Classifier: Topic :: System :: Hardware
Classifier: Programming Language :: Python
Classifier: Operating System :: MacOS :: MacOS X
Classifier: Operating System :: Microsoft :: Windows
Classifier: Operating System :: POSIX
License-File: COPYING
Requires-Dist: ftd2xx>=1.3.8
Dynamic: author
Dynamic: author-email
Dynamic: classifier
Dynamic: description
Dynamic: description-content-type
Dynamic: home-page
Dynamic: keywords
Dynamic: license
Dynamic: maintainer
Dynamic: maintainer-email
Dynamic: requires-dist
Dynamic: summary
